docclassifier/__init__.py
docclassifier/classifier.py
docclassifier/margin_based/__init__.py
docclassifier/margin_based/infer.py
docclassifier_docsaid-0.10.1.dist-info/LICENSE
docclassifier_docsaid-0.10.1.dist-info/METADATA
docclassifier_docsaid-0.10.1.dist-info/WHEEL
docclassifier_docsaid-0.10.1.dist-info/top_level.txt
docclassifier_docsaid-0.10.1.dist-info/RECORD
